actpdf/__init__.py
actpdf/base.html
actpdf/base_genomaxx.html
actpdf/base_qua.html
actpdf/generate_pdfs.py
actpdf/templates/allergy/sample.json
actpdf/templates/allergy/template.html
actpdf/templates/allergy/images/.gitignore
actpdf/templates/allergy/images/back.jpg
actpdf/templates/allergy/images/cover.jpg
actpdf/templates/allergy/static_pages/disclaimer.txt
actpdf/templates/allergy/static_pages/how_to.txt
actpdf/templates/allergy/static_pages/intro.txt
actpdf/templates/carrier/template.html
actpdf/templates/carrier/images/back.jpg
actpdf/templates/carrier/images/cover.jpg
actpdf/templates/carrier/static_pages/disclaimer.txt
actpdf/templates/carrier/static_pages/how_to.txt
actpdf/templates/carrier/static_pages/intro.txt
actpdf/templates/detox/template.html
actpdf/templates/detox/images/.gitignore
actpdf/templates/detox/images/back.png
actpdf/templates/detox/images/cover.png
actpdf/templates/detox/static_pages/disclaimer.txt
actpdf/templates/detox/static_pages/how_to.txt
actpdf/templates/detox/static_pages/intro.txt
actpdf/templates/disease/template.html
actpdf/templates/fitness/template.html
actpdf/templates/fitness/images/.gitignore
actpdf/templates/fitness/images/back.jpg
actpdf/templates/fitness/images/cover.jpg
actpdf/templates/fitness/images/front_plain.png
actpdf/templates/fitness/static_pages/disclaimer.txt
actpdf/templates/fitness/static_pages/how_to.txt
actpdf/templates/fitness/static_pages/intro.txt
actpdf/templates/fitness_quanutrition/template.html
actpdf/templates/fitness_quanutrition/images/.gitignore
actpdf/templates/fitness_quanutrition/images/back.jpg
actpdf/templates/fitness_quanutrition/images/cover.jpg
actpdf/templates/fitness_quanutrition/images/graph_average.png
actpdf/templates/fitness_quanutrition/images/graph_danger.png
actpdf/templates/fitness_quanutrition/images/graph_positive.png
actpdf/templates/fitness_quanutrition/static_pages/disclaimer.txt
actpdf/templates/fitness_quanutrition/static_pages/how_to.txt
actpdf-0.12.dist-info/METADATA
actpdf-0.12.dist-info/WHEEL
actpdf-0.12.dist-info/entry_points.txt
actpdf-0.12.dist-info/top_level.txt
actpdf-0.12.dist-info/RECORD
