Metadata-Version: 2.1
Name: actpdf
Version: 0.12
Summary: act pdf generator. we build act pdfs from json files.
Home-page: https://github.com/gamifications/actpdf
Author: Suhail VS
Author-email: suhailvs@gmail.com
Project-URL: Bug Tracker, https://github.com/gamifications/actpdf/issues
Classifier: Programming Language :: Python :: 3
Classifier: Programming Language :: Python :: 3.8
Classifier: Programming Language :: Python :: 3.9
Classifier: License :: OSI Approved :: MIT License
Classifier: Operating System :: OS Independent
Requires-Python: >=3.6
Requires-Dist: weasyprint (==52.4)
Requires-Dist: jinja2
Requires-Dist: Markdown
Requires-Dist: pygal
Requires-Dist: matplotlib
